{
  "id": "lit_edbd5b934db8",
  "sessionId": "idea_101d2097ed88",
  "title": "Effectiveness of liquid smoke as a preservative agent of barracuda fish cake during cold storage",
  "authors": [
    "Y. Febriani",
    "F. Swastawati",
    "Sumardianto",
    "A. Fahmi",
    "Romadhon"
  ],
  "venue": "IOP Conference Series: Earth and Environment",
  "year": 2023,
  "url": "https://www.semanticscholar.org/paper/cce76644c515613b2e83fc633b1d596a232fb517",
  "doi": "10.1088/1755-1315/1224/1/012033",
  "arxivId": null,
  "snippet": "Barracuda is one species of white fleshed fish that has a soft texture and a savoury taste, therefore it can be processed into fish cakes. Fish cake is a perishable food caused by bacterial activity that can be prevented using preservative namely liquid smoke. The addition of liquid smoke can provide an extended shelf life and a unique taste sensation in fish cakes because it functions as an antibacterial. The purpose of the study was to determine the role of liquid smoke in increasing the shelf",
  "relevanceScore": 0.9,
  "source": "semantic_scholar",
  "createdAt": "2026-05-13T15:56:43.575176"
}